README.rst
setup.py
tinydb_git/__init__.py
tinydb_git/json.py
tinydb_git/yaml.py
tinydb_git.egg-info/PKG-INFO
tinydb_git.egg-info/SOURCES.txt
tinydb_git.egg-info/dependency_links.txt
tinydb_git.egg-info/requires.txt
tinydb_git.egg-info/top_level.txt