Metadata-Version: 1.1
Name: tinydb-git
Version: 0.2
Summary: A git-based storage backend for tinydb.
Home-page: https://github.com/mbr/tinydb-git
Author: Marc Brinkmann
Author-email: git@marcbrinkmann.de
License: MIT
Platform: UNKNOWN
Classifier: Programming Language :: Python :: 2
Classifier: Programming Language :: Python :: 3
